tdecomp/__init__.py
tdecomp/_base.py
tdecomp/output_formats.py
tdecomp/utils.py
tdecomp/grad_proj/__init__.py
tdecomp/grad_proj/tensorgrad/__init__.py
tdecomp/grad_proj/tensorgrad/config.py
tdecomp/grad_proj/tensorgrad/mem_trace.py
tdecomp/grad_proj/tensorgrad/prepared_tg.py
tdecomp/grad_proj/tensorgrad/setup_optimizer.py
tdecomp/grad_proj/tensorgrad/tensorgrad.py
tdecomp/grad_proj/tensorgrad/projectors/__init__.py
tdecomp/grad_proj/tensorgrad/projectors/galore_projector.py
tdecomp/grad_proj/tensorgrad/projectors/projector_utils.py
tdecomp/grad_proj/tensorgrad/projectors/sparse_projector.py
tdecomp/grad_proj/tensorgrad/projectors/tensor_lowrank_projector.py
tdecomp/grad_proj/tensorgrad/projectors/tensor_sparse_projector.py
tdecomp/grad_proj/tensorgrad/projectors/tensor_unstructured_sparse_projector.py
tdecomp/grad_proj/tensorgrad/training_utils/__init__.py
tdecomp/grad_proj/tensorgrad/training_utils/get_scheduler.py
tdecomp/grad_proj/tensorgrad/training_utils/training_state.py
tdecomp/grad_proj/tensorgrad/training_utils/training_state_async.py
tdecomp/matrix/__init__.py
tdecomp/matrix/decomposer.py
tdecomp/matrix/functional.py
tdecomp/matrix/random_projections.py
tdecomp/tensor/__init__.py
tdecomp-0.2.18.dist-info/METADATA
tdecomp-0.2.18.dist-info/WHEEL
tdecomp-0.2.18.dist-info/top_level.txt
tdecomp-0.2.18.dist-info/RECORD
