Metadata-Version: 2.4
Name: tdecomp
Version: 0.2.18
Summary: Library for tensor and matrix decompositions applications
Home-page: https://github.com/leostre/tensor-decompositions.git
Author: Leon Strelkov
Author-email: strelllleo@mail.ru
License:  BSD License
Keywords: tensor decompositions,matrix decompositions,randomized algorithms
Classifier: License :: OSI Approved :: BSD License
Classifier: Programming Language :: Python :: 3.8
Classifier: Programming Language :: Python :: 3.9
Classifier: Programming Language :: Python :: 3.10
Requires-Python: >=3.8
Requires-Dist: tensorly
Requires-Dist: torch
Dynamic: author
Dynamic: author-email
Dynamic: classifier
Dynamic: description
Dynamic: description-content-type
Dynamic: home-page
Dynamic: keywords
Dynamic: license
Dynamic: requires-dist
Dynamic: requires-python
Dynamic: summary
